dwcontents/__init__.py
dwcontents/api.py
dwcontents/contents.py
dwcontents/hybridcontents.py
dwcontents/models.py
dwcontents/utils.py
dwcontents-1.0.0b5.dist-info/DESCRIPTION.rst
dwcontents-1.0.0b5.dist-info/METADATA
dwcontents-1.0.0b5.dist-info/RECORD
dwcontents-1.0.0b5.dist-info/WHEEL
dwcontents-1.0.0b5.dist-info/entry_points.txt
dwcontents-1.0.0b5.dist-info/metadata.json
dwcontents-1.0.0b5.dist-info/top_level.txt
