Metadata-Version: 2.0
Name: dwcontents
Version: 1.0.0b5
Summary: Jupyter contents manager for data.world
Home-page: http://github.com/datadotworld/dw-jupyter-contents
Author: data.world
Author-email: help@data.world
License: Apache 2.0
Keywords: data.world dataset
Platform: UNKNOWN
Classifier: Development Status :: 4 - Beta
Classifier: Framework :: IPython
Classifier: Framework :: Jupyter
Classifier: Intended Audience :: Developers
Classifier: Intended Audience :: Science/Research
Classifier: License :: OSI Approved :: Apache Software License
Classifier: Operating System :: OS Independent
Classifier: Programming Language :: Python :: 2
Classifier: Programming Language :: Python :: 2.7
Classifier: Programming Language :: Python :: 3
Classifier: Programming Language :: Python :: 3.4
Classifier: Programming Language :: Python :: 3.5
Classifier: Programming Language :: Python :: 3.6
Classifier: Topic :: Database :: Database Engines/Servers
Classifier: Topic :: Scientific/Engineering
Classifier: Topic :: Software Development :: Libraries :: Python Modules
Requires-Dist: backoff (<2.0a,>=1.3.0)
Requires-Dist: certifi (>=2017.04.17)
Requires-Dist: datadotworld (>=1.1.0,<2.0a)
Requires-Dist: flake8 (>=2.6.0,<4.0a)
Requires-Dist: ipython (<=6.0a,>=4.0)
Requires-Dist: notebook (<=6.0a,>=4.0)
Requires-Dist: requests (>=2.0.0,<3.0a)
Requires-Dist: six (>=1.5.0,<2.0a)
Provides-Extra: pandas
Requires-Dist: pandas (<1.0a); extra == 'pandas'
